espnfantasyfootball/__init__.py
espnfantasyfootball/espnfantasyfootball.py
espnfantasyfootball-0.1.1.dist-info/METADATA
espnfantasyfootball-0.1.1.dist-info/WHEEL
espnfantasyfootball-0.1.1.dist-info/top_level.txt
espnfantasyfootball-0.1.1.dist-info/RECORD
