Metadata-Version: 2.1
Name: espnfantasyfootball
Version: 0.1.1
Summary: A Python package to interact with ESPN Fantasy Football data
Home-page: https://github.com/tbryan2/espnfantasyfootball
Author: Tim Bryan
License: MIT
Platform: UNKNOWN
